monocdk_serverless_clamscan/__init__.py
monocdk_serverless_clamscan/py.typed
monocdk_serverless_clamscan/_jsii/__init__.py
monocdk_serverless_clamscan/_jsii/monocdk-serverless-clamscan@1.2.18.jsii.tgz
monocdk_serverless_clamscan-1.2.18.data/scripts/0
monocdk_serverless_clamscan-1.2.18.dist-info/LICENSE
monocdk_serverless_clamscan-1.2.18.dist-info/METADATA
monocdk_serverless_clamscan-1.2.18.dist-info/NOTICE
monocdk_serverless_clamscan-1.2.18.dist-info/WHEEL
monocdk_serverless_clamscan-1.2.18.dist-info/top_level.txt
monocdk_serverless_clamscan-1.2.18.dist-info/RECORD
